{
    "created_at": "Fri Aug 24 11:59:35 +0000 2018",
    "display_text_range": [
        "0",
        "167"
    ],
    "entities": {
        "hashtags": [
            {
                "indices": [
                    "121",
                    "126"
                ],
                "text": "FRUS"
            },
            {
                "indices": [
                    "127",
                    "143"
                ],
                "text": "twitterstorians"
            }
        ],
        "media": [
            {
                "display_url": "pic.x.com/FIvH2OuOQc",
                "expanded_url": "https://x.com/HistoryAtState/status/1032960610479300609/photo/1",
                "id": "1032960431378313219",
                "id_str": "1032960431378313219",
                "indices": [
                    "144",
                    "167"
                ],
                "media_url": "http://pbs.twimg.com/media/DlXQChtWsAMmecm.jpg",
                "media_url_https": "https://pbs.twimg.com/media/DlXQChtWsAMmecm.jpg",
                "sizes": {
                    "large": {
                        "h": "600",
                        "resize": "fit",
                        "w": "400"
                    },
                    "medium": {
                        "h": "600",
                        "resize": "fit",
                        "w": "400"
                    },
                    "small": {
                        "h": "600",
                        "resize": "fit",
                        "w": "400"
                    },
                    "thumb": {
                        "h": "150",
                        "resize": "crop",
                        "w": "150"
                    }
                },
                "type": "photo",
                "url": "https://t.co/FIvH2OuOQc"
            }
        ],
        "symbols": [],
        "urls": [
            {
                "display_url": "history.state.gov/historicaldocu…",
                "expanded_url": "https://history.state.gov/historicaldocuments/quarterly-releases/2018-q3",
                "indices": [
                    "97",
                    "120"
                ],
                "url": "https://t.co/ZQyYdlXM3B"
            }
        ],
        "user_mentions": []
    },
    "extended_entities": {
        "media": [
            {
                "display_url": "pic.x.com/FIvH2OuOQc",
                "expanded_url": "https://x.com/HistoryAtState/status/1032960610479300609/photo/1",
                "id": "1032960431378313219",
                "id_str": "1032960431378313219",
                "indices": [
                    "144",
                    "167"
                ],
                "media_url": "http://pbs.twimg.com/media/DlXQChtWsAMmecm.jpg",
                "media_url_https": "https://pbs.twimg.com/media/DlXQChtWsAMmecm.jpg",
                "sizes": {
                    "large": {
                        "h": "600",
                        "resize": "fit",
                        "w": "400"
                    },
                    "medium": {
                        "h": "600",
                        "resize": "fit",
                        "w": "400"
                    },
                    "small": {
                        "h": "600",
                        "resize": "fit",
                        "w": "400"
                    },
                    "thumb": {
                        "h": "150",
                        "resize": "crop",
                        "w": "150"
                    }
                },
                "type": "photo",
                "url": "https://t.co/FIvH2OuOQc"
            }
        ]
    },
    "favorite_count": "6",
    "favorited": false,
    "full_text": "15 newly-digitized Foreign Relations volumes covering events between 1866 and 1873 now available https://t.co/ZQyYdlXM3B #FRUS #twitterstorians https://t.co/FIvH2OuOQc",
    "id": "1032960610479300609",
    "id_str": "1032960610479300609",
    "lang": "en",
    "possibly_sensitive": false,
    "retweet_count": "5",
    "retweeted": false,
    "source": "&lt;a href=\"http://twitter.com\" rel=\"nofollow\"&gt;Twitter Web Client&lt;/a&gt;",
    "truncated": false
}
