{
    "contributors": null,
    "coordinates": null,
    "created_at": "Wed Oct 23 15:33:28 +0000 2019",
    "display_text_range": [
        0,
        144
    ],
    "entities": {
        "hashtags": [],
        "symbols": [],
        "urls": [],
        "user_mentions": [
            {
                "id": 958044239576948740,
                "id_str": "958044239576948736",
                "indices": [
                    3,
                    14
                ],
                "name": "Foreign Service Institute",
                "screen_name": "FSIatState"
            }
        ]
    },
    "favorite_count": 0,
    "favorited": false,
    "full_text": "RT @FSIatState: Did you know U.S. diplomatic officers responded to unprecedented challenges as they protected U.S. citizens &amp;amp; facilitated h…",
    "geo": null,
    "id": 1187029279395270660,
    "id_str": "1187029279395270656",
    "in_reply_to_screen_name": null,
    "in_reply_to_status_id": null,
    "in_reply_to_status_id_str": null,
    "in_reply_to_user_id": null,
    "in_reply_to_user_id_str": null,
    "is_quote_status": false,
    "lang": "en",
    "place": null,
    "retweet_count": 1,
    "retweeted": true,
    "retweeted_status": {
        "contributors": null,
        "coordinates": null,
        "created_at": "Wed Oct 23 14:44:22 +0000 2019",
        "display_text_range": [
            0,
            248
        ],
        "entities": {
            "hashtags": [
                {
                    "indices": [
                        198,
                        218
                    ],
                    "text": "HeroesofUSDiplomacy"
                }
            ],
            "media": [
                {
                    "display_url": "pic.twitter.com/wpZRjTEOQv",
                    "expanded_url": "https://twitter.com/FSIatState/status/1187016921599954944/photo/1",
                    "id": 1187016917955043330,
                    "id_str": "1187016917955043328",
                    "indices": [
                        249,
                        272
                    ],
                    "media_url": "http://pbs.twimg.com/media/EHkhmQkW4AAvruy.jpg",
                    "media_url_https": "https://pbs.twimg.com/media/EHkhmQkW4AAvruy.jpg",
                    "sizes": {
                        "large": {
                            "h": 512,
                            "resize": "fit",
                            "w": 1024
                        },
                        "medium": {
                            "h": 512,
                            "resize": "fit",
                            "w": 1024
                        },
                        "small": {
                            "h": 340,
                            "resize": "fit",
                            "w": 680
                        },
                        "thumb": {
                            "h": 150,
                            "resize": "crop",
                            "w": 150
                        }
                    },
                    "type": "photo",
                    "url": "https://t.co/wpZRjTEOQv"
                }
            ],
            "symbols": [],
            "urls": [
                {
                    "display_url": "go.usa.gov/xp3FN",
                    "expanded_url": "http://go.usa.gov/xp3FN",
                    "indices": [
                        225,
                        248
                    ],
                    "url": "https://t.co/4D5leJ3WJC"
                }
            ],
            "user_mentions": []
        },
        "extended_entities": {
            "media": [
                {
                    "display_url": "pic.twitter.com/wpZRjTEOQv",
                    "expanded_url": "https://twitter.com/FSIatState/status/1187016921599954944/photo/1",
                    "ext_alt_text": null,
                    "id": 1187016917955043330,
                    "id_str": "1187016917955043328",
                    "indices": [
                        249,
                        272
                    ],
                    "media_url": "http://pbs.twimg.com/media/EHkhmQkW4AAvruy.jpg",
                    "media_url_https": "https://pbs.twimg.com/media/EHkhmQkW4AAvruy.jpg",
                    "sizes": {
                        "large": {
                            "h": 512,
                            "resize": "fit",
                            "w": 1024
                        },
                        "medium": {
                            "h": 512,
                            "resize": "fit",
                            "w": 1024
                        },
                        "small": {
                            "h": 340,
                            "resize": "fit",
                            "w": 680
                        },
                        "thumb": {
                            "h": 150,
                            "resize": "crop",
                            "w": 150
                        }
                    },
                    "type": "photo",
                    "url": "https://t.co/wpZRjTEOQv"
                }
            ]
        },
        "favorite_count": 1,
        "favorited": false,
        "full_text": "Did you know U.S. diplomatic officers responded to unprecedented challenges as they protected U.S. citizens &amp;amp; facilitated humanitarian relief efforts during World War I?  Learn more about these #HeroesofUSDiplomacy here: https://t.co/4D5leJ3WJC https://t.co/wpZRjTEOQv",
        "geo": null,
        "id": 1187016921599954940,
        "id_str": "1187016921599954944",
        "in_reply_to_screen_name": null,
        "in_reply_to_status_id": null,
        "in_reply_to_status_id_str": null,
        "in_reply_to_user_id": null,
        "in_reply_to_user_id_str": null,
        "is_quote_status": false,
        "lang": "en",
        "place": null,
        "possibly_sensitive": false,
        "retweet_count": 1,
        "retweeted": true,
        "source": "&lt;a href=\"https://mobile.twitter.com\" rel=\"nofollow\"&gt;Twitter Web App&lt;/a&gt;",
        "truncated": false,
        "user": {
            "id": 958044239576948740,
            "id_str": "958044239576948736"
        }
    },
    "source": "&lt;a href=\"https://mobile.twitter.com\" rel=\"nofollow\"&gt;Twitter Web App&lt;/a&gt;",
    "truncated": false,
    "user": {
        "id": 586570880,
        "id_str": "586570880"
    }
}
