{
    "created_at": "Fri Mar 12 18:02:02 +0000 2021",
    "display_text_range": [
        "0",
        "237"
    ],
    "entities": {
        "hashtags": [
            {
                "indices": [
                    "208",
                    "212"
                ],
                "text": "HAC"
            }
        ],
        "symbols": [],
        "urls": [
            {
                "display_url": "history.state.gov/historicaldocu…",
                "expanded_url": "https://history.state.gov/historicaldocuments/frus-history/chapter-8",
                "indices": [
                    "214",
                    "237"
                ],
                "url": "https://t.co/np837l2yoz"
            }
        ],
        "user_mentions": []
    },
    "favorite_count": "6",
    "favorited": false,
    "full_text": "OH mourns the passing of Walter LaFeber, who served first as a member and then as chair of the Department of State's Historical Advisory Committee (HAC) in the early 1970s. You can read about his time on the #HAC:\nhttps://t.co/np837l2yoz",
    "id": "1370434928060547082",
    "id_str": "1370434928060547082",
    "lang": "en",
    "possibly_sensitive": false,
    "retweet_count": "0",
    "retweeted": false,
    "source": "&lt;a href=\"https://www.hootsuite.com\" rel=\"nofollow\"&gt;Hootsuite Inc.&lt;/a&gt;",
    "truncated": false
}
