{
    "created_at": "Wed Oct 27 20:01:29 +0000 2021",
    "display_text_range": [
        "0",
        "237"
    ],
    "entities": {
        "hashtags": [
            {
                "indices": [
                    "3",
                    "16"
                ],
                "text": "FavoriteFRUS"
            }
        ],
        "media": [
            {
                "display_url": "pic.x.com/chV6y2aSmo",
                "expanded_url": "https://x.com/HistoryAtState/status/1453451809985597440/photo/1",
                "id": "1453451808026861571",
                "id_str": "1453451808026861571",
                "indices": [
                    "214",
                    "237"
                ],
                "media_url": "http://pbs.twimg.com/media/FCuyt_uXIAMyPMI.png",
                "media_url_https": "https://pbs.twimg.com/media/FCuyt_uXIAMyPMI.png",
                "sizes": {
                    "large": {
                        "h": "1508",
                        "resize": "fit",
                        "w": "964"
                    },
                    "medium": {
                        "h": "1200",
                        "resize": "fit",
                        "w": "767"
                    },
                    "small": {
                        "h": "680",
                        "resize": "fit",
                        "w": "435"
                    },
                    "thumb": {
                        "h": "150",
                        "resize": "crop",
                        "w": "150"
                    }
                },
                "type": "photo",
                "url": "https://t.co/chV6y2aSmo"
            }
        ],
        "symbols": [],
        "urls": [
            {
                "display_url": "ow.ly/4yxe50GtS66",
                "expanded_url": "http://ow.ly/4yxe50GtS66",
                "indices": [
                    "183",
                    "206"
                ],
                "url": "https://t.co/G2LB10Fybz"
            }
        ],
        "user_mentions": []
    },
    "extended_entities": {
        "media": [
            {
                "display_url": "pic.x.com/chV6y2aSmo",
                "expanded_url": "https://x.com/HistoryAtState/status/1453451809985597440/photo/1",
                "id": "1453451808026861571",
                "id_str": "1453451808026861571",
                "indices": [
                    "214",
                    "237"
                ],
                "media_url": "http://pbs.twimg.com/media/FCuyt_uXIAMyPMI.png",
                "media_url_https": "https://pbs.twimg.com/media/FCuyt_uXIAMyPMI.png",
                "sizes": {
                    "large": {
                        "h": "1508",
                        "resize": "fit",
                        "w": "964"
                    },
                    "medium": {
                        "h": "1200",
                        "resize": "fit",
                        "w": "767"
                    },
                    "small": {
                        "h": "680",
                        "resize": "fit",
                        "w": "435"
                    },
                    "thumb": {
                        "h": "150",
                        "resize": "crop",
                        "w": "150"
                    }
                },
                "type": "photo",
                "url": "https://t.co/chV6y2aSmo"
            }
        ]
    },
    "favorite_count": "7",
    "favorited": false,
    "full_text": "No #FavoriteFRUS list would be complete without one of our earliest volumes: the compilation of worldwide condolences sent to the United States on the assassination of Pres. Lincoln:\nhttps://t.co/G2LB10Fybz\n\n(1/2) https://t.co/chV6y2aSmo",
    "id": "1453451809985597440",
    "id_str": "1453451809985597440",
    "lang": "en",
    "possibly_sensitive": false,
    "retweet_count": "2",
    "retweeted": false,
    "source": "&lt;a href=\"https://www.hootsuite.com\" rel=\"nofollow\"&gt;Hootsuite Inc.&lt;/a&gt;",
    "truncated": false
}
