[
    {
        "created_at": "Fri Oct 29 23:30:09 +0000 2021",
        "id": 1454229095181656071,
        "id_str": "1454229095181656071",
        "full_text": "Powell \u201cgave the State Department the very best of his leadership, his experience, his patriotism. He gave us his decency, and the State Department loved him for it. Secretary Powell trusted the career workforce here; he empowered them.\u201d\n\u2014Secretary Blinken, Oct. 18, 2021 https://t.co/PqhP1y766h",
        "truncated": false,
        "display_text_range": [
            0,
            271
        ],
        "entities": {
            "hashtags": [],
            "symbols": [],
            "user_mentions": [],
            "urls": [],
            "media": [
                {
                    "id": 1454229093340393476,
                    "id_str": "1454229093340393476",
                    "indices": [
                        272,
                        295
                    ],
                    "media_url": "http://pbs.twimg.com/media/FC51p9KXsAQ3x8w.png",
                    "media_url_https": "https://pbs.twimg.com/media/FC51p9KXsAQ3x8w.png",
                    "url": "https://t.co/PqhP1y766h",
                    "display_url": "pic.twitter.com/PqhP1y766h",
                    "expanded_url": "https://twitter.com/HistoryAtState/status/1454229095181656071/photo/1",
                    "type": "photo",
                    "sizes": {
                        "small": {
                            "w": 680,
                            "h": 416,
                            "resize": "fit"
                        },
                        "medium": {
                            "w": 1200,
                            "h": 734,
                            "resize": "fit"
                        },
                        "thumb": {
                            "w": 150,
                            "h": 150,
                            "resize": "crop"
                        },
                        "large": {
                            "w": 1710,
                            "h": 1046,
                            "resize": "fit"
                        }
                    }
                }
            ]
        },
        "extended_entities": {
            "media": [
                {
                    "id": 1454229093340393476,
                    "id_str": "1454229093340393476",
                    "indices": [
                        272,
                        295
                    ],
                    "media_url": "http://pbs.twimg.com/media/FC51p9KXsAQ3x8w.png",
                    "media_url_https": "https://pbs.twimg.com/media/FC51p9KXsAQ3x8w.png",
                    "url": "https://t.co/PqhP1y766h",
                    "display_url": "pic.twitter.com/PqhP1y766h",
                    "expanded_url": "https://twitter.com/HistoryAtState/status/1454229095181656071/photo/1",
                    "type": "photo",
                    "sizes": {
                        "small": {
                            "w": 680,
                            "h": 416,
                            "resize": "fit"
                        },
                        "medium": {
                            "w": 1200,
                            "h": 734,
                            "resize": "fit"
                        },
                        "thumb": {
                            "w": 150,
                            "h": 150,
                            "resize": "crop"
                        },
                        "large": {
                            "w": 1710,
                            "h": 1046,
                            "resize": "fit"
                        }
                    }
                }
            ]
        },
        "source": "\u003ca href=\"https://www.hootsuite.com\" rel=\"nofollow\"\u003eHootsuite Inc.\u003c/a\u003e",
        "in_reply_to_status_id": null,
        "in_reply_to_status_id_str": null,
        "in_reply_to_user_id": null,
        "in_reply_to_user_id_str": null,
        "in_reply_to_screen_name": null,
        "user": {
            "id": 586570880,
            "id_str": "586570880"
        },
        "geo": null,
        "coordinates": null,
        "place": null,
        "contributors": null,
        "is_quote_status": false,
        "retweet_count": 0,
        "favorite_count": 5,
        "favorited": false,
        "retweeted": false,
        "possibly_sensitive": false,
        "lang": "en"
    }
]