{
    "created_at": "Mon Aug 28 22:01:15 +0000 2023",
    "display_text_range": [
        "0",
        "279"
    ],
    "entities": {
        "hashtags": [],
        "media": [
            {
                "display_url": "pic.x.com/8FtGsTOAxn",
                "expanded_url": "https://x.com/HistoryAtState/status/1696281816263508280/video/1",
                "id": "1696280325435895808",
                "id_str": "1696280325435895808",
                "indices": [
                    "256",
                    "279"
                ],
                "media_url": "http://pbs.twimg.com/ext_tw_video_thumb/1696280325435895808/pu/img/d3I3-QT0YiBQ_jaE.jpg",
                "media_url_https": "https://pbs.twimg.com/ext_tw_video_thumb/1696280325435895808/pu/img/d3I3-QT0YiBQ_jaE.jpg",
                "sizes": {
                    "large": {
                        "h": "720",
                        "resize": "fit",
                        "w": "1280"
                    },
                    "medium": {
                        "h": "675",
                        "resize": "fit",
                        "w": "1200"
                    },
                    "small": {
                        "h": "383",
                        "resize": "fit",
                        "w": "680"
                    },
                    "thumb": {
                        "h": "150",
                        "resize": "crop",
                        "w": "150"
                    }
                },
                "type": "photo",
                "url": "https://t.co/8FtGsTOAxn"
            }
        ],
        "symbols": [],
        "urls": [
            {
                "display_url": "ow.ly/on1f50PF9kH",
                "expanded_url": "https://ow.ly/on1f50PF9kH",
                "indices": [
                    "196",
                    "219"
                ],
                "url": "https://t.co/y5tIcFWGOU"
            },
            {
                "display_url": "ow.ly/4BzV50PF9kO",
                "expanded_url": "https://ow.ly/4BzV50PF9kO",
                "indices": [
                    "232",
                    "255"
                ],
                "url": "https://t.co/0d59qcg0JO"
            }
        ],
        "user_mentions": [
            {
                "id": "586570880",
                "id_str": "586570880",
                "indices": [
                    "142",
                    "157"
                ],
                "name": "HistoryAtState",
                "screen_name": "HistoryAtState"
            }
        ]
    },
    "extended_entities": {
        "media": [
            {
                "additional_media_info": {
                    "monetizable": false
                },
                "display_url": "pic.x.com/8FtGsTOAxn",
                "expanded_url": "https://x.com/HistoryAtState/status/1696281816263508280/video/1",
                "id": "1696280325435895808",
                "id_str": "1696280325435895808",
                "indices": [
                    "256",
                    "279"
                ],
                "media_url": "http://pbs.twimg.com/ext_tw_video_thumb/1696280325435895808/pu/img/d3I3-QT0YiBQ_jaE.jpg",
                "media_url_https": "https://pbs.twimg.com/ext_tw_video_thumb/1696280325435895808/pu/img/d3I3-QT0YiBQ_jaE.jpg",
                "sizes": {
                    "large": {
                        "h": "720",
                        "resize": "fit",
                        "w": "1280"
                    },
                    "medium": {
                        "h": "675",
                        "resize": "fit",
                        "w": "1200"
                    },
                    "small": {
                        "h": "383",
                        "resize": "fit",
                        "w": "680"
                    },
                    "thumb": {
                        "h": "150",
                        "resize": "crop",
                        "w": "150"
                    }
                },
                "type": "video",
                "url": "https://t.co/8FtGsTOAxn",
                "video_info": {
                    "aspect_ratio": [
                        "16",
                        "9"
                    ],
                    "duration_millis": "28966",
                    "variants": [
                        {
                            "content_type": "application/x-mpegURL",
                            "url": "https://video.twimg.com/ext_tw_video/1696280325435895808/pu/pl/4BYdfSKpxHdPrcwA.m3u8?tag=12"
                        },
                        {
                            "bitrate": "832000",
                            "content_type": "video/mp4",
                            "url": "https://video.twimg.com/ext_tw_video/1696280325435895808/pu/vid/640x360/j2nBAk9Ph20No8oi.mp4?tag=12"
                        },
                        {
                            "bitrate": "2176000",
                            "content_type": "video/mp4",
                            "url": "https://video.twimg.com/ext_tw_video/1696280325435895808/pu/vid/1280x720/OI4WSzQHqcNFwHb3.mp4?tag=12"
                        },
                        {
                            "bitrate": "256000",
                            "content_type": "video/mp4",
                            "url": "https://video.twimg.com/ext_tw_video/1696280325435895808/pu/vid/480x270/Tju1-HNIAQ_-xtwi.mp4?tag=12"
                        }
                    ]
                }
            }
        ]
    },
    "favorite_count": "0",
    "favorited": false,
    "full_text": "Quick with the quips and steady with the (proverbial) red pen? Current/former federal employee eligible for competitive service? Apply to the @HistoryAtState Editing and Publishing Team!\n• GS-13: https://t.co/y5tIcFWGOU\n• GS-11/12: https://t.co/0d59qcg0JO https://t.co/8FtGsTOAxn",
    "id": "1696281816263508280",
    "id_str": "1696281816263508280",
    "lang": "en",
    "possibly_sensitive": false,
    "retweet_count": "0",
    "retweeted": false,
    "source": "&lt;a href=\"https://www.hootsuite.com\" rel=\"nofollow\"&gt;Hootsuite Inc.&lt;/a&gt;",
    "truncated": false
}
