{
    "created_at": "Tue Sep 05 13:01:33 +0000 2023",
    "display_text_range": [
        "0",
        "273"
    ],
    "entities": {
        "hashtags": [],
        "media": [
            {
                "display_url": "pic.x.com/O7sH1kyvik",
                "expanded_url": "https://x.com/HistoryAtState/status/1699045101161365754/video/1",
                "id": "1699043523562016768",
                "id_str": "1699043523562016768",
                "indices": [
                    "250",
                    "273"
                ],
                "media_url": "http://pbs.twimg.com/ext_tw_video_thumb/1699043523562016768/pu/img/bqIykv_7Dc7jg3Nj.jpg",
                "media_url_https": "https://pbs.twimg.com/ext_tw_video_thumb/1699043523562016768/pu/img/bqIykv_7Dc7jg3Nj.jpg",
                "sizes": {
                    "large": {
                        "h": "720",
                        "resize": "fit",
                        "w": "1280"
                    },
                    "medium": {
                        "h": "675",
                        "resize": "fit",
                        "w": "1200"
                    },
                    "small": {
                        "h": "383",
                        "resize": "fit",
                        "w": "680"
                    },
                    "thumb": {
                        "h": "150",
                        "resize": "crop",
                        "w": "150"
                    }
                },
                "type": "photo",
                "url": "https://t.co/O7sH1kyvik"
            }
        ],
        "symbols": [],
        "urls": [
            {
                "display_url": "ow.ly/N8XG50PF6cx",
                "expanded_url": "https://ow.ly/N8XG50PF6cx",
                "indices": [
                    "190",
                    "213"
                ],
                "url": "https://t.co/gZ7xfh2pHQ"
            },
            {
                "display_url": "ow.ly/UEo050PF6cR",
                "expanded_url": "https://ow.ly/UEo050PF6cR",
                "indices": [
                    "226",
                    "249"
                ],
                "url": "https://t.co/FEdjEKMyR5"
            }
        ],
        "user_mentions": [
            {
                "id": "586570880",
                "id_str": "586570880",
                "indices": [
                    "128",
                    "143"
                ],
                "name": "HistoryAtState",
                "screen_name": "HistoryAtState"
            }
        ]
    },
    "extended_entities": {
        "media": [
            {
                "additional_media_info": {
                    "monetizable": false
                },
                "display_url": "pic.x.com/O7sH1kyvik",
                "expanded_url": "https://x.com/HistoryAtState/status/1699045101161365754/video/1",
                "id": "1699043523562016768",
                "id_str": "1699043523562016768",
                "indices": [
                    "250",
                    "273"
                ],
                "media_url": "http://pbs.twimg.com/ext_tw_video_thumb/1699043523562016768/pu/img/bqIykv_7Dc7jg3Nj.jpg",
                "media_url_https": "https://pbs.twimg.com/ext_tw_video_thumb/1699043523562016768/pu/img/bqIykv_7Dc7jg3Nj.jpg",
                "sizes": {
                    "large": {
                        "h": "720",
                        "resize": "fit",
                        "w": "1280"
                    },
                    "medium": {
                        "h": "675",
                        "resize": "fit",
                        "w": "1200"
                    },
                    "small": {
                        "h": "383",
                        "resize": "fit",
                        "w": "680"
                    },
                    "thumb": {
                        "h": "150",
                        "resize": "crop",
                        "w": "150"
                    }
                },
                "type": "video",
                "url": "https://t.co/O7sH1kyvik",
                "video_info": {
                    "aspect_ratio": [
                        "16",
                        "9"
                    ],
                    "duration_millis": "14100",
                    "variants": [
                        {
                            "bitrate": "2176000",
                            "content_type": "video/mp4",
                            "url": "https://video.twimg.com/ext_tw_video/1699043523562016768/pu/vid/avc1/1280x720/GD3wUR2b_HsI95qh.mp4?tag=12"
                        },
                        {
                            "bitrate": "832000",
                            "content_type": "video/mp4",
                            "url": "https://video.twimg.com/ext_tw_video/1699043523562016768/pu/vid/avc1/640x360/dXwhotW_Ck3pBkrY.mp4?tag=12"
                        },
                        {
                            "bitrate": "256000",
                            "content_type": "video/mp4",
                            "url": "https://video.twimg.com/ext_tw_video/1699043523562016768/pu/vid/avc1/480x270/0rmimUbhvLf1RtFL.mp4?tag=12"
                        },
                        {
                            "content_type": "application/x-mpegURL",
                            "url": "https://video.twimg.com/ext_tw_video/1699043523562016768/pu/pl/Bn7e4nFGVuHpaJHY.m3u8?tag=12"
                        }
                    ]
                }
            }
        ]
    },
    "favorite_count": "0",
    "favorited": false,
    "full_text": "🎵 Have style? Have flair? Are you there?†\nThat’s how you’ll become a canny… 🎶\nhistorian with the Editing and Publishing Team at @HistoryAtState!\n\n† Details on USAJOBS—⚠️ DUE TODAY:\n• GS-13: https://t.co/gZ7xfh2pHQ\n• GS-11/12: https://t.co/FEdjEKMyR5 https://t.co/O7sH1kyvik",
    "id": "1699045101161365754",
    "id_str": "1699045101161365754",
    "lang": "en",
    "possibly_sensitive": false,
    "retweet_count": "0",
    "retweeted": false,
    "source": "&lt;a href=\"https://www.hootsuite.com\" rel=\"nofollow\"&gt;Hootsuite Inc.&lt;/a&gt;",
    "truncated": false
}
