[
    {
        "created_at": "Mon Jul 09 13:54:36 +0000 2012",
        "id": 222327900857307137,
        "id_str": "222327900857307137",
        "full_text": "VSFS applications are open! Students interested in eInterning for the Historian\u2019s Office can apply http://t.co/wzTwn0ZQ #twitterstorians",
        "truncated": false,
        "display_text_range": [
            0,
            136
        ],
        "entities": {
            "hashtags": [
                {
                    "text": "twitterstorians",
                    "indices": [
                        120,
                        136
                    ]
                }
            ],
            "symbols": [],
            "user_mentions": [],
            "urls": [
                {
                    "url": "http://t.co/wzTwn0ZQ",
                    "expanded_url": "http://go.usa.gov/vzp",
                    "display_url": "go.usa.gov/vzp",
                    "indices": [
                        99,
                        119
                    ]
                }
            ]
        },
        "source": "\u003ca href=\"http://twitter.com\" rel=\"nofollow\"\u003eTwitter Web Client\u003c/a\u003e",
        "in_reply_to_status_id": null,
        "in_reply_to_status_id_str": null,
        "in_reply_to_user_id": null,
        "in_reply_to_user_id_str": null,
        "in_reply_to_screen_name": null,
        "user": {
            "id": 586570880,
            "id_str": "586570880"
        },
        "geo": null,
        "coordinates": null,
        "place": null,
        "contributors": null,
        "is_quote_status": false,
        "retweet_count": 1,
        "favorite_count": 0,
        "favorited": false,
        "retweeted": false,
        "possibly_sensitive": false,
        "lang": "en"
    }
]