{
    "created_at": "Wed Aug 29 17:04:11 +0000 2012",
    "display_text_range": [
        "0",
        "139"
    ],
    "entities": {
        "hashtags": [
            {
                "indices": [
                    "117",
                    "122"
                ],
                "text": "FRUS"
            },
            {
                "indices": [
                    "123",
                    "139"
                ],
                "text": "twitterstorians"
            }
        ],
        "symbols": [],
        "urls": [
            {
                "display_url": "go.usa.gov/rN8x",
                "expanded_url": "http://go.usa.gov/rN8x",
                "indices": [
                    "96",
                    "116"
                ],
                "url": "http://t.co/kNBRpjR9"
            }
        ],
        "user_mentions": []
    },
    "favorite_count": "3",
    "favorited": false,
    "full_text": "The Office of the Historian releases Foreign Relations, Foundations of Foreign Policy, 1973-76. http://t.co/kNBRpjR9 #FRUS #twitterstorians",
    "id": "240857388960321538",
    "id_str": "240857388960321538",
    "lang": "en",
    "possibly_sensitive": false,
    "retweet_count": "21",
    "retweeted": false,
    "source": "&lt;a href=\"http://twitter.com\" rel=\"nofollow\"&gt;Twitter Web Client&lt;/a&gt;",
    "truncated": false
}
