{
    "created_at": "Sat Jan 05 20:01:22 +0000 2013",
    "id": 287650013214015488,
    "id_str": "287650013214015488",
    "full_text": "Join us at #AHA2013 as we discuss the Office's recent launch of #FRUS as #ebooks. http://t.co/OCSuvQjU #twitterstorians",
    "truncated": false,
    "display_text_range": [
        0,
        119
    ],
    "entities": {
        "hashtags": [
            {
                "text": "AHA2013",
                "indices": [
                    11,
                    19
                ]
            },
            {
                "text": "FRUS",
                "indices": [
                    64,
                    69
                ]
            },
            {
                "text": "ebooks",
                "indices": [
                    73,
                    80
                ]
            },
            {
                "text": "twitterstorians",
                "indices": [
                    103,
                    119
                ]
            }
        ],
        "symbols": [],
        "user_mentions": [],
        "urls": [
            {
                "url": "http://t.co/OCSuvQjU",
                "expanded_url": "http://bit.ly/URLiqy",
                "display_url": "bit.ly/URLiqy",
                "indices": [
                    82,
                    102
                ]
            }
        ]
    },
    "source": "&lt;a href=\"http://www.hootsuite.com\" rel=\"nofollow\"&gt;Hootsuite&lt;/a&gt;",
    "in_reply_to_status_id": null,
    "in_reply_to_status_id_str": null,
    "in_reply_to_user_id": null,
    "in_reply_to_user_id_str": null,
    "in_reply_to_screen_name": null,
    "user": {
        "id": 586570880,
        "id_str": "586570880"
    },
    "geo": null,
    "coordinates": null,
    "place": null,
    "contributors": null,
    "is_quote_status": false,
    "retweet_count": 3,
    "favorite_count": 0,
    "favorited": false,
    "retweeted": false,
    "possibly_sensitive": false,
    "lang": "en"
}