{
    "contributors": null,
    "coordinates": null,
    "created_at": "Thu May 23 16:30:36 +0000 2013",
    "display_text_range": [
        0,
        120
    ],
    "entities": {
        "hashtags": [
            {
                "indices": [
                    28,
                    36
                ],
                "text": "opengov"
            },
            {
                "indices": [
                    111,
                    120
                ],
                "text": "opendata"
            }
        ],
        "symbols": [],
        "urls": [
            {
                "display_url": "Data.gov",
                "expanded_url": "http://Data.gov",
                "indices": [
                    48,
                    70
                ],
                "url": "http://t.co/FFhOQRgZZT"
            },
            {
                "display_url": "1.usa.gov/1ab3li0",
                "expanded_url": "http://1.usa.gov/1ab3li0",
                "indices": [
                    88,
                    110
                ],
                "url": "http://t.co/SAIdVLNk3N"
            }
        ],
        "user_mentions": [
            {
                "id": 94642927,
                "id_str": "94642927",
                "indices": [
                    3,
                    13
                ],
                "name": "Data.gov",
                "screen_name": "usdatagov"
            }
        ]
    },
    "favorite_count": 0,
    "favorited": false,
    "full_text": "RT @usdatagov: Opensourcing #opengov with a new http://t.co/FFhOQRgZZT catalog and APIs http://t.co/SAIdVLNk3N #opendata",
    "geo": null,
    "id": 337606498291154940,
    "id_str": "337606498291154944",
    "in_reply_to_screen_name": null,
    "in_reply_to_status_id": null,
    "in_reply_to_status_id_str": null,
    "in_reply_to_user_id": null,
    "in_reply_to_user_id_str": null,
    "is_quote_status": false,
    "lang": "en",
    "place": null,
    "possibly_sensitive": false,
    "retweet_count": 10,
    "retweeted": true,
    "retweeted_status": {
        "contributors": null,
        "coordinates": null,
        "created_at": "Thu May 23 12:16:55 +0000 2013",
        "display_text_range": [
            0,
            105
        ],
        "entities": {
            "hashtags": [
                {
                    "indices": [
                        13,
                        21
                    ],
                    "text": "opengov"
                },
                {
                    "indices": [
                        96,
                        105
                    ],
                    "text": "opendata"
                }
            ],
            "symbols": [],
            "urls": [
                {
                    "display_url": "Data.gov",
                    "expanded_url": "http://Data.gov",
                    "indices": [
                        33,
                        55
                    ],
                    "url": "http://t.co/FFhOQRgZZT"
                },
                {
                    "display_url": "1.usa.gov/1ab3li0",
                    "expanded_url": "http://1.usa.gov/1ab3li0",
                    "indices": [
                        73,
                        95
                    ],
                    "url": "http://t.co/SAIdVLNk3N"
                }
            ],
            "user_mentions": []
        },
        "favorite_count": 2,
        "favorited": false,
        "full_text": "Opensourcing #opengov with a new http://t.co/FFhOQRgZZT catalog and APIs http://t.co/SAIdVLNk3N #opendata",
        "geo": null,
        "id": 337542658933272580,
        "id_str": "337542658933272576",
        "in_reply_to_screen_name": null,
        "in_reply_to_status_id": null,
        "in_reply_to_status_id_str": null,
        "in_reply_to_user_id": null,
        "in_reply_to_user_id_str": null,
        "is_quote_status": false,
        "lang": "en",
        "place": null,
        "possibly_sensitive": false,
        "retweet_count": 10,
        "retweeted": true,
        "source": "&lt;a href=\"https://about.twitter.com/products/tweetdeck\" rel=\"nofollow\"&gt;TweetDeck&lt;/a&gt;",
        "truncated": false,
        "user": {
            "id": 94642927,
            "id_str": "94642927"
        }
    },
    "source": "&lt;a href=\"http://twitter.com\" rel=\"nofollow\"&gt;Twitter Web Client&lt;/a&gt;",
    "truncated": false,
    "user": {
        "id": 586570880,
        "id_str": "586570880"
    }
}
