[
    {
        "created_at": "Wed Aug 07 12:04:02 +0000 2013",
        "id": 365080893284548608,
        "id_str": "365080893284548608",
        "full_text": "#OTD 1927 #SecState Frank Kellog attended dedication of the \u201cPeace Bridge\u201d btw Buffalo, NY &amp; Ft. Erie, Canada http://t.co/k9yS691HOR",
        "truncated": false,
        "display_text_range": [
            0,
            136
        ],
        "entities": {
            "hashtags": [
                {
                    "text": "OTD",
                    "indices": [
                        0,
                        4
                    ]
                },
                {
                    "text": "SecState",
                    "indices": [
                        10,
                        19
                    ]
                }
            ],
            "symbols": [],
            "user_mentions": [],
            "urls": [
                {
                    "url": "http://t.co/k9yS691HOR",
                    "expanded_url": "http://go.usa.gov/jNpG",
                    "display_url": "go.usa.gov/jNpG",
                    "indices": [
                        114,
                        136
                    ]
                }
            ]
        },
        "source": "\u003ca href=\"http://www.hootsuite.com\" rel=\"nofollow\"\u003eHootsuite\u003c/a\u003e",
        "in_reply_to_status_id": null,
        "in_reply_to_status_id_str": null,
        "in_reply_to_user_id": null,
        "in_reply_to_user_id_str": null,
        "in_reply_to_screen_name": null,
        "user": {
            "id": 586570880,
            "id_str": "586570880"
        },
        "geo": null,
        "coordinates": null,
        "place": null,
        "contributors": null,
        "is_quote_status": false,
        "retweet_count": 0,
        "favorite_count": 0,
        "favorited": false,
        "retweeted": false,
        "possibly_sensitive": false,
        "lang": "en"
    }
]