{
    "contributors": null,
    "coordinates": null,
    "created_at": "Tue Dec 24 14:07:42 +0000 2013",
    "display_text_range": [
        0,
        76
    ],
    "entities": {
        "hashtags": [
            {
                "indices": [
                    35,
                    40
                ],
                "text": "FRUS"
            }
        ],
        "symbols": [],
        "urls": [
            {
                "display_url": "go.usa.gov/WSG5",
                "expanded_url": "http://go.usa.gov/WSG5",
                "indices": [
                    54,
                    76
                ],
                "url": "http://t.co/1wuLZJ5gHr"
            }
        ],
        "user_mentions": []
    },
    "favorite_count": 0,
    "favorited": false,
    "full_text": "See how partisan impulses affected #FRUS in the 1950s http://t.co/1wuLZJ5gHr",
    "geo": null,
    "id": 415483926329585660,
    "id_str": "415483926329585665",
    "in_reply_to_screen_name": null,
    "in_reply_to_status_id": null,
    "in_reply_to_status_id_str": null,
    "in_reply_to_user_id": null,
    "in_reply_to_user_id_str": null,
    "is_quote_status": false,
    "lang": "en",
    "place": null,
    "possibly_sensitive": false,
    "retweet_count": 3,
    "retweeted": false,
    "source": "&lt;a href=\"http://www.hootsuite.com\" rel=\"nofollow\"&gt;Hootsuite&lt;/a&gt;",
    "truncated": false,
    "user": {
        "id": 586570880,
        "id_str": "586570880"
    }
}
