{
    "created_at": "Mon Feb 17 13:20:19 +0000 2014",
    "display_text_range": [
        "0",
        "130"
    ],
    "entities": {
        "hashtags": [
            {
                "indices": [
                    "15",
                    "24"
                ],
                "text": "SecState"
            },
            {
                "indices": [
                    "35",
                    "41"
                ],
                "text": "POTUS"
            }
        ],
        "symbols": [],
        "urls": [
            {
                "display_url": "go.usa.gov/ByJY",
                "expanded_url": "http://go.usa.gov/ByJY",
                "indices": [
                    "108",
                    "130"
                ],
                "url": "http://t.co/hMfSY2hazZ"
            }
        ],
        "user_mentions": [
            {
                "id": "9624742",
                "id_str": "9624742",
                "indices": [
                    "4",
                    "14"
                ],
                "name": "Department of State",
                "screen_name": "StateDept"
            }
        ]
    },
    "favorite_count": "8",
    "favorited": false,
    "full_text": "Six @StateDept #SecState served as #POTUS: Jefferson, Madison, Monroe, JQA, Van Buren, Buchanan. Learn more http://t.co/hMfSY2hazZ",
    "id": "435403338117824512",
    "id_str": "435403338117824512",
    "lang": "en",
    "possibly_sensitive": false,
    "retweet_count": "22",
    "retweeted": false,
    "source": "&lt;a href=\"http://www.hootsuite.com\" rel=\"nofollow\"&gt;Hootsuite&lt;/a&gt;",
    "truncated": false
}
