[
    {
        "created_at": "Thu Jul 17 14:57:13 +0000 2014",
        "id": 489785902118748160,
        "id_str": "489785902118748160",
        "full_text": "Diplomatic life, cultural events &amp; literary pursuits: US Min. to Belgium Brand Whitlock settles into Brussels 1914 http://t.co/zMnHlANQI8",
        "truncated": false,
        "display_text_range": [
            0,
            141
        ],
        "entities": {
            "hashtags": [],
            "symbols": [],
            "user_mentions": [],
            "urls": [
                {
                    "url": "http://t.co/zMnHlANQI8",
                    "expanded_url": "http://ow.ly/zgRbx",
                    "display_url": "ow.ly/zgRbx",
                    "indices": [
                        119,
                        141
                    ]
                }
            ]
        },
        "source": "\u003ca href=\"http://www.hootsuite.com\" rel=\"nofollow\"\u003eHootsuite\u003c/a\u003e",
        "in_reply_to_status_id": null,
        "in_reply_to_status_id_str": null,
        "in_reply_to_user_id": null,
        "in_reply_to_user_id_str": null,
        "in_reply_to_screen_name": null,
        "user": {
            "id": 586570880,
            "id_str": "586570880"
        },
        "geo": null,
        "coordinates": null,
        "place": null,
        "contributors": null,
        "is_quote_status": false,
        "retweet_count": 2,
        "favorite_count": 0,
        "favorited": false,
        "retweeted": false,
        "possibly_sensitive": false,
        "lang": "en"
    }
]