{
    "created_at": "Sun Aug 03 14:00:58 +0000 2014",
    "display_text_range": [
        "0",
        "130"
    ],
    "entities": {
        "hashtags": [
            {
                "indices": [
                    "0",
                    "5"
                ],
                "text": "TDiH"
            },
            {
                "indices": [
                    "98",
                    "107"
                ],
                "text": "WW1Tweet"
            }
        ],
        "symbols": [],
        "urls": [
            {
                "display_url": "go.usa.gov/5MeR",
                "expanded_url": "http://go.usa.gov/5MeR",
                "indices": [
                    "108",
                    "130"
                ],
                "url": "http://t.co/bkP8YSC9bR"
            }
        ],
        "user_mentions": [
            {
                "id": "14856951",
                "id_str": "14856951",
                "indices": [
                    "11",
                    "19"
                ],
                "name": "U.S. Embassy London",
                "screen_name": "USAinUK"
            }
        ]
    },
    "favorite_count": "0",
    "favorited": false,
    "full_text": "#TDiH 1914 @USAinUK Amb Page reports on conditions, diplomatic war news &amp;amp; influx of Americans #WW1Tweet http://t.co/bkP8YSC9bR",
    "id": "495932339877609474",
    "id_str": "495932339877609474",
    "lang": "en",
    "possibly_sensitive": false,
    "retweet_count": "1",
    "retweeted": false,
    "source": "&lt;a href=\"http://www.hootsuite.com\" rel=\"nofollow\"&gt;Hootsuite&lt;/a&gt;",
    "truncated": false
}
