{
    "created_at": "Mon Nov 23 14:32:14 +0000 2015",
    "display_text_range": [
        "0",
        "129"
    ],
    "entities": {
        "hashtags": [
            {
                "indices": [
                    "107",
                    "112"
                ],
                "text": "FRUS"
            },
            {
                "indices": [
                    "113",
                    "129"
                ],
                "text": "twitterstorians"
            }
        ],
        "symbols": [],
        "urls": [
            {
                "display_url": "go.usa.gov/caK64",
                "expanded_url": "http://go.usa.gov/caK64",
                "indices": [
                    "83",
                    "106"
                ],
                "url": "https://t.co/38ztnv7kz2"
            }
        ],
        "user_mentions": []
    },
    "favorite_count": "0",
    "favorited": false,
    "full_text": "Interested in the Treaty of Tlatelolco and the nuclear free zone in Latin America? https://t.co/38ztnv7kz2 #FRUS #twitterstorians",
    "id": "668799219738812416",
    "id_str": "668799219738812416",
    "lang": "en",
    "possibly_sensitive": false,
    "retweet_count": "2",
    "retweeted": false,
    "source": "&lt;a href=\"http://www.hootsuite.com\" rel=\"nofollow\"&gt;Hootsuite&lt;/a&gt;",
    "truncated": false
}
