{
    "created_at": "Mon Dec 07 13:03:07 +0000 2015",
    "display_text_range": [
        "0",
        "134"
    ],
    "entities": {
        "hashtags": [
            {
                "indices": [
                    "112",
                    "117"
                ],
                "text": "FRUS"
            },
            {
                "indices": [
                    "118",
                    "134"
                ],
                "text": "twitterstorians"
            }
        ],
        "symbols": [],
        "urls": [
            {
                "display_url": "history.state.gov/historicaldocu…",
                "expanded_url": "https://history.state.gov/historicaldocuments/frus1945v06",
                "indices": [
                    "88",
                    "111"
                ],
                "url": "https://t.co/PNTVrlOcYg"
            }
        ],
        "user_mentions": []
    },
    "favorite_count": "0",
    "favorited": false,
    "full_text": "Now available: Foreign Relations, 1945, The British Commonwealth, The Far East, Vol. VI https://t.co/PNTVrlOcYg #FRUS #twitterstorians",
    "id": "673850223354118146",
    "id_str": "673850223354118146",
    "lang": "en",
    "possibly_sensitive": false,
    "retweet_count": "0",
    "retweeted": false,
    "source": "&lt;a href=\"http://www.hootsuite.com\" rel=\"nofollow\"&gt;Hootsuite&lt;/a&gt;",
    "truncated": false
}
