[
    {
        "created_at": "Tue Nov 08 19:20:19 +0000 2016",
        "id": 796069858274410497,
        "id_str": "796069858274410497",
        "full_text": "LBJ admin weighs 1968 election impact on Vietnam War. https://t.co/F49726PIEH #FRUS #twitterstorians #election2016",
        "truncated": false,
        "display_text_range": [
            0,
            114
        ],
        "entities": {
            "hashtags": [
                {
                    "text": "FRUS",
                    "indices": [
                        78,
                        83
                    ]
                },
                {
                    "text": "twitterstorians",
                    "indices": [
                        84,
                        100
                    ]
                },
                {
                    "text": "election2016",
                    "indices": [
                        101,
                        114
                    ]
                }
            ],
            "symbols": [],
            "user_mentions": [],
            "urls": [
                {
                    "url": "https://t.co/F49726PIEH",
                    "expanded_url": "http://go.usa.gov/xksEE",
                    "display_url": "go.usa.gov/xksEE",
                    "indices": [
                        54,
                        77
                    ]
                }
            ]
        },
        "source": "\u003ca href=\"http://www.hootsuite.com\" rel=\"nofollow\"\u003eHootsuite\u003c/a\u003e",
        "in_reply_to_status_id": null,
        "in_reply_to_status_id_str": null,
        "in_reply_to_user_id": null,
        "in_reply_to_user_id_str": null,
        "in_reply_to_screen_name": null,
        "user": {
            "id": 586570880,
            "id_str": "586570880"
        },
        "geo": null,
        "coordinates": null,
        "place": null,
        "contributors": null,
        "is_quote_status": false,
        "retweet_count": 2,
        "favorite_count": 1,
        "favorited": false,
        "retweeted": false,
        "possibly_sensitive": false,
        "lang": "en"
    }
]