[
    {
        "created_at": "Mon Jan 09 21:20:20 +0000 2017",
        "id": 818568111221800960,
        "id_str": "818568111221800960",
        "full_text": "\u201cOur students went out and put up our flag in violation of our understanding.\u201d #LBJ #OTD #FRUS #PanamaCanal        https://t.co/ysChELHOYy",
        "truncated": false,
        "display_text_range": [
            0,
            138
        ],
        "entities": {
            "hashtags": [
                {
                    "text": "LBJ",
                    "indices": [
                        79,
                        83
                    ]
                },
                {
                    "text": "OTD",
                    "indices": [
                        84,
                        88
                    ]
                },
                {
                    "text": "FRUS",
                    "indices": [
                        89,
                        94
                    ]
                },
                {
                    "text": "PanamaCanal",
                    "indices": [
                        95,
                        107
                    ]
                }
            ],
            "symbols": [],
            "user_mentions": [],
            "urls": [
                {
                    "url": "https://t.co/ysChELHOYy",
                    "expanded_url": "http://go.usa.gov/x928K",
                    "display_url": "go.usa.gov/x928K",
                    "indices": [
                        115,
                        138
                    ]
                }
            ]
        },
        "source": "\u003ca href=\"http://www.hootsuite.com\" rel=\"nofollow\"\u003eHootsuite\u003c/a\u003e",
        "in_reply_to_status_id": null,
        "in_reply_to_status_id_str": null,
        "in_reply_to_user_id": null,
        "in_reply_to_user_id_str": null,
        "in_reply_to_screen_name": null,
        "user": {
            "id": 586570880,
            "id_str": "586570880"
        },
        "geo": null,
        "coordinates": null,
        "place": null,
        "contributors": null,
        "is_quote_status": false,
        "retweet_count": 0,
        "favorite_count": 0,
        "favorited": false,
        "retweeted": false,
        "possibly_sensitive": false,
        "lang": "en"
    }
]