{
    "created_at": "Wed Feb 21 16:05:08 +0000 2018",
    "display_text_range": [
        "0",
        "252"
    ],
    "entities": {
        "hashtags": [
            {
                "indices": [
                    "66",
                    "74"
                ],
                "text": "Liberia"
            },
            {
                "indices": [
                    "76",
                    "88"
                ],
                "text": "SouthAfrica"
            },
            {
                "indices": [
                    "94",
                    "104"
                ],
                "text": "Australia"
            },
            {
                "indices": [
                    "217",
                    "233"
                ],
                "text": "Twitterstorians"
            },
            {
                "indices": [
                    "234",
                    "252"
                ],
                "text": "BlackHistoryMonth"
            }
        ],
        "symbols": [],
        "urls": [
            {
                "display_url": "go.usa.gov/xnFt5",
                "expanded_url": "https://go.usa.gov/xnFt5",
                "indices": [
                    "193",
                    "216"
                ],
                "url": "https://t.co/XWcZeJSTTS"
            }
        ],
        "user_mentions": [
            {
                "id": "3433322913",
                "id_str": "3433322913",
                "indices": [
                    "119",
                    "127"
                ],
                "name": "@StateDG",
                "screen_name": "StateDG"
            }
        ]
    },
    "favorite_count": "1",
    "favorited": false,
    "full_text": "Edward J. Perkins was appointed Ambassador to the United Nations, #Liberia, #SouthAfrica, and #Australia. He served as @StateDG and retired with rank of Career Minister in the Foreign Service. https://t.co/XWcZeJSTTS #Twitterstorians #BlackHistoryMonth",
    "id": "966343037025734656",
    "id_str": "966343037025734656",
    "lang": "en",
    "possibly_sensitive": false,
    "retweet_count": "1",
    "retweeted": false,
    "source": "&lt;a href=\"http://www.hootsuite.com\" rel=\"nofollow\"&gt;Hootsuite&lt;/a&gt;",
    "truncated": false
}
